setup.py
datastore/__init__.py
datastore.git.egg-info/PKG-INFO
datastore.git.egg-info/SOURCES.txt
datastore.git.egg-info/dependency_links.txt
datastore.git.egg-info/namespace_packages.txt
datastore.git.egg-info/requires.txt
datastore.git.egg-info/top_level.txt
datastore/git/__init__.py
datastore/git/test.py