Metadata-Version: 1.0
Name: datastore.git
Version: 0.1.1
Summary: git datastore implementation
Home-page: http://github.com/datastore/datastore.git
Author: Juan Batiz-Benet
Author-email: juan@benet.ai
License: MIT License
Keywords: datastore,git,dulwich
Platform: UNKNOWN
Classifier: Topic :: Database
Classifier: Topic :: Database :: Front-Ends
